<?xml version="1.0" encoding="utf-8"?> 

<release_note>


<version>0.5.2.0</version>
<title>Release notes (selected features and issues only)</title>
<lines></lines>
<lines>* SkillTable beautified</lines>
<lines>* ConfirmActions beautified</lines>
<lines>* ExtraPlayerInfo as new module</lines>
<lines>* ContextMenuCopyId with added HT-ML tags </lines>
<lines>* CopyPostID with added HT-ML tag</lines>
<lines>* CopyPosting with HT-ML tags as default</lines>
<lines>* Added basic functionality for all missing HT languages </lines>

<lines></lines> 
<lines>Attention!</lines>
<lines>*Ticker and alerts have been moved to an own tab.</lines>
 	
<lines></lines> 
<lines>It's recommended to use the 'set new features' link bellow.</lines> 




</release_note>
