<language name="lt" desc="Lietuvių">

	<!-- the 6 strings from the hts menue line. used for language autodetection. copy "value"-->
	<MyHattrick value="Mano Hattrick" />
	<MyClub value="Mano komanda" />
	<World value="Pasaulis" />
	<Forum value="Forumai" />
	<Shop value="Parduotuvė" />
	<Help value="Pagalba" />

	<!-- rating sublevels appearing in match detail page. copy "text" -->
	<ratingSubLevels>
		<sublevel text="(min.)" value="0.0" />
		<sublevel text="(žemas)" value="0.25" />
		<sublevel text="(aukštas)" value="0.50" />
		<sublevel text="(maks.)" value="0.75" />
	</ratingSubLevels>

	<!-- tactics appearing in match detail page. copy "value" -->
	<tactics>
		<tactic type="normal" value="Normalus" />
		<tactic type="pressing" value="Spaudimas" />
		<tactic type="ca" value="Kontratakos" />
		<tactic type="aow" value="Atakos kraštais" />
		<tactic type="aim" value="Atakos centru" />
		<tactic type="creatively" value="Žaisti išradingai" />
		<tactic type="longshots" value="Tolimi smūgiai" />
	</tactics>

	<!-- positions appearing on players page. copy "value". translate "short" -->
	<positions>
		<position type="Keeper" value="Vartininkas" short="Vr" />
		<position type="Central defender" value="Vidurio gynėjas" short="Cg" />
		<position type="Wing back" value="Krašto gynėjas" short="Kg" />
		<position type="Inner midfielder" value="Saugas" short="Cs" />
		<position type="Winger" value="Krašto saugas" short="Ks" />
		<position type="Forward" value="Puolėjas" short="Pl" />
	</positions>

	<!-- specialties appearing on players page. copy "value". translate "short" -->
	<specialties>
		<specialty type="Unpredictable" value="Nenuspėjamas" short="Un" />
		<specialty type="Powerful" value="Stiprus" short="Po" />
		<specialty type="Quick" value="Greitas" short="Qu" />
		<specialty type="Technical" value="Techniškas" short="Te" />
		<specialty type="Head" value="Aukštas" short="He" />
		<specialty type="Regainer" value="Atsigaunantis" short="Re" />
	</specialties>

	<!-- levels word connections appearing denominations page. copy "text" -->
	<levels>
		<level text="dieviškas" value="20" />
		<level text="utopinis" value="19" />
		<level text="magiškas" value="18" />
		<level text="mistinis" value="17" />
		<level text="nežemiškas" value="16" />
		<level text="gigantiškas" value="15" />
		<level text="antgamtiškas" value="14" />
		<level text="pasaulinės klasės" value="13" />
		<level text="fantastiškas" value="12" />
		<level text="genialus" value="11" />
		<level text="išskirtinis" value="10" />
		<level text="nuostabus" value="9" />
		<level text="puikus" value="8" />
		<level text="geras" value="7" />
		<level text="priimtinas" value="6" />
		<level text="vidutiniškas" value="5" />
		<level text="silpnas" value="4" />
		<level text="menkas" value="3" />
		<level text="apgailėtinas" value="2" />
		<level text="katastrofiškas" value="1" />
		<level text="neegzistuojantis" value="0" />
	</levels>
</language>
