<language name="pl" desc="Polski">

	<!-- the 6 strings from the hts menue line. used for language autodetection. copy "value"-->
	<MyHattrick value="Mój Hattrick" />
	<MyClub value="Mój Klub" />
	<World value="Świat" />
	<Forum value="Forum" />
	<Shop value="Sklep" />
	<Help value="Pomoc" />

	<!-- rating sublevels appearing in match detail page. copy "text" -->
	<ratingSubLevels>
		<sublevel text="(min.)" value="0.0" />
		<sublevel text="(niski)" value="0.25" />
		<sublevel text="(wysoki)" value="0.50" />
		<sublevel text="(maks.)" value="0.75" />
	</ratingSubLevels>

	<!-- tactics appearing in match detail page. copy "value" -->
	<tactics>
		<tactic type="normal" value="normalny" />
		<tactic type="pressing" value="Pressing" />
		<tactic type="ca" value="Gra z kontry" />
		<tactic type="aow" value="Atak skrzydłami" />
		<tactic type="aim" value="Atak środkiem" />
		<tactic type="creatively" value="Gra kreatywna" />
		<tactic type="longshots" value="Strzały z dystansu" />
	</tactics>

	<!-- positions appearing on players page. copy "value". translate "short" -->
	<positions>
		<position type="Keeper" value="bramkarz" short="Ke" />
		<position type="Central defender" value="środkowy obrońca" short="Cd" />
		<position type="Wing back" value="boczny obrońca" short="Wb" />
		<position type="Inner midfielder" value="środkowy pomocnik" short="Im" />
		<position type="Winger" value="skrzydłowy" short="Wi" />
		<position type="Forward" value="napastnik" short="Fo" />
	</positions>

	<!-- specialties appearing on players page. copy "value". translate "short" -->
	<specialties>
		<specialty type="Unpredictable" value="nieprzewidywalny" short="Un" />
		<specialty type="Powerful" value="atletyczny" short="Po" />
		<specialty type="Quick" value="szybki" short="Qu" />
		<specialty type="Technical" value="techniczny" short="Te" />
		<specialty type="Head" value="gra głową" short="He" />
		<specialty type="Regainer" value="witalny" short="Re" />
	</specialties>

	<!-- levels word connections appearing denominations page. copy "text" -->
	<levels>
		<level text="boski" value="20" />
		<level text="utopijny" value="19" />
		<level text="magiczny" value="18" />
		<level text="mityczny" value="17" />
		<level text="nieziemski" value="16" />
		<level text="tytaniczny" value="15" />
		<level text="nadprzyrodzony" value="14" />
		<level text="światowej klasy" value="13" />
		<level text="mistrzowski" value="12" />
		<level text="błyskotliwy" value="11" />
		<level text="olśniewający" value="10" />
		<level text="fantastyczny" value="9" />
		<level text="znakomity" value="8" />
		<level text="solidny" value="7" />
		<level text="zadowalający" value="6" />
		<level text="przeciętny" value="5" />
		<level text="słaby" value="4" />
		<level text="kiepski" value="3" />
		<level text="nędzny" value="2" />
		<level text="fatalny" value="1" />
		<level text="beznadziejny" value="0" />
	</levels>
	
	<!-- Agreeability levels in denominations page.
	     Translate attribute "text" by copying from there in verbatim,
	     keep attribute "value" unchanged. -->
	<agreeability>
		<level text="uwielbiany przez zespół" value="5"/>
		<level text="popularny" value="4"/>
		<level text="sympatyczny" value="3"/>
		<level text="przyjemny" value="2"/>
		<level text="kontrowersyjny" value="1"/>
		<level text="złośliwy" value="0"/>
	</agreeability>
	
	<!-- Honesty levels in denominations page.
	     Translate attribute "text" by copying from there in verbatim,
	     keep attribute "value" unchanged. -->
	<honesty>
		<level text="świątobliwy" value="5"/>
		<level text="szlachetny" value="4"/>
		<level text="prawy" value="3"/>
		<level text="uczciwy" value="2"/>
		<level text="nieuczciwy" value="1"/>
		<level text="podły" value="0"/>
	</honesty>
	
	<!-- Aggressiveness levels in denominations page.
	     Translate attribute "text" by copying from there in verbatim,
	     keep attribute "value" unchanged. -->
	<aggressiveness>
		<level text="niezrównoważony" value="5"/>
		<level text="porywczy" value="4"/>
		<level text="z charakterem" value="3"/>
		<level text="zrównoważony" value="2"/>
		<level text="opanowany" value="1"/>
		<level text="spokojny" value="0"/>
	</aggressiveness>
</language>
